{"data":[{"data":{"user":{"id":"119657765","videos":{"edges":[{"cursor":null,"node":{"animatedPreviewURL":"https:\/\/dgeft87wbj63p.cloudfront.net\/b65155a821e994107a83_maximebiaggi_46498103532_1673550034\/storyboards\/1705327394-strip-0.jpg","game":{"boxArtURL":"https:\/\/static-cdn.jtvnw.net\/ttv-boxart\/509658-40x56.jpg","id":"509658","displayName":"Just Chatting","name":"Just Chatting","__typename":"Game"},"id":"1705327394","lengthSeconds":7690,"owner":{"displayName":"MaximeBiaggi","id":"119657765","login":"maximebiaggi","profileImageURL":"https:\/\/static-cdn.jtvnw.net\/jtv_user_pictures\/994ba4ea-98ba-4446-a923-164e575ff498-profile_image-50x50.png","primaryColorHex":"0013A3","__typename":"User"},"previewThumbnailURL":"https:\/\/static-cdn.jtvnw.net\/cf_vods\/dgeft87wbj63p\/b65155a821e994107a83_maximebiaggi_46498103532_1673550034\/\/thumb\/thumb0-320x180.jpg","publishedAt":"2023-01-12T19:00:39Z","self":{"isRestricted":false,"viewingHistory":null,"__typename":"VideoSelfEdge"},"title":"On regarde mon passage dans les 12 coups de midi d'il y a 7 ans !!!!!!!!!!!!!!!!!!!!!!!!!!!!!!!!!!!!!!!!","viewCount":207008,"resourceRestriction":null,"contentTags":[{"id":"6f655045-9989-4ef7-8f85-1edcec42d648","isLanguageTag":true,"localizedName":"French","tagName":"auto___lang_fr","__typename":"Tag"}],"__typename":"Video"},"__typename":"VideoEdge"},{"cursor":null,"node":{"animatedPreviewURL":"https:\/\/dgeft87wbj63p.cloudfront.net\/75e4f0efcb5560e14ab3_maximebiaggi_46490705884_1673373846\/storyboards\/1703380034-strip-0.jpg","game":{"boxArtURL":"https:\/\/static-cdn.jtvnw.net\/ttv-boxart\/509658-40x56.jpg","id":"509658","displayName":"Just Chatting","name":"Just Chatting","__typename":"Game"},"id":"1703380034","lengthSeconds":12471,"owner":{"displayName":"MaximeBiaggi","id":"119657765","login":"maximebiaggi","profileImageURL":"https:\/\/static-cdn.jtvnw.net\/jtv_user_pictures\/994ba4ea-98ba-4446-a923-164e575ff498-profile_image-50x50.png","primaryColorHex":"0013A3","__typename":"User"},"previewThumbnailURL":"https:\/\/static-cdn.jtvnw.net\/cf_vods\/dgeft87wbj63p\/75e4f0efcb5560e14ab3_maximebiaggi_46490705884_1673373846\/\/thumb\/thumb0-320x180.jpg","publishedAt":"2023-01-10T18:04:10Z","self":{"isRestricted":false,"viewingHistory":null,"__typename":"VideoSelfEdge"},"title":"Blabla debrief emission puis games de LoL ? Peut \u00eatre..","viewCount":129425,"resourceRestriction":null,"contentTags":[{"id":"6f655045-9989-4ef7-8f85-1edcec42d648","isLanguageTag":true,"localizedName":"French","tagName":"auto___lang_fr","__typename":"Tag"}],"__typename":"Video"},"__typename":"VideoEdge"},{"cursor":null,"node":{"animatedPreviewURL":"https:\/\/dgeft87wbj63p.cloudfront.net\/c59c28d1e6fbbc1d1762_maximebiaggi_46487598332_1673290233\/storyboards\/1702492418-strip-0.jpg","game":{"boxArtURL":"https:\/\/static-cdn.jtvnw.net\/ttv-boxart\/417752-40x56.jpg","id":"417752","displayName":"Talk Shows & Podcasts","name":"Talk Shows & Podcasts","__typename":"Game"},"id":"1702492418","lengthSeconds":7983,"owner":{"displayName":"MaximeBiaggi","id":"119657765","login":"maximebiaggi","profileImageURL":"https:\/\/static-cdn.jtvnw.net\/jtv_user_pictures\/994ba4ea-98ba-4446-a923-164e575ff498-profile_image-50x50.png","primaryColorHex":"0013A3","__typename":"User"},"previewThumbnailURL":"https:\/\/static-cdn.jtvnw.net\/cf_vods\/dgeft87wbj63p\/c59c28d1e6fbbc1d1762_maximebiaggi_46487598332_1673290233\/\/thumb\/thumb0-320x180.jpg","publishedAt":"2023-01-09T18:50:38Z","self":{"isRestricted":false,"viewingHistory":null,"__typename":"VideoSelfEdge"},"title":"ZEN ! On est en plateau avec Mcfly & Carlito (tr\u00e8s grosse \u00e9mission...)","viewCount":357768,"resourceRestriction":null,"contentTags":[{"id":"6f655045-9989-4ef7-8f85-1edcec42d648","isLanguageTag":true,"localizedName":"French","tagName":"auto___lang_fr","__typename":"Tag"}],"__typename":"Video"},"__typename":"VideoEdge"},{"cursor":null,"node":{"animatedPreviewURL":"https:\/\/dgeft87wbj63p.cloudfront.net\/412dade1b7eb0d02fddb_maximebiaggi_46485027756_1673207991\/storyboards\/1701662946-strip-0.jpg","game":{"boxArtURL":"https:\/\/static-cdn.jtvnw.net\/ttv-boxart\/509658-40x56.jpg","id":"509658","displayName":"Just Chatting","name":"Just Chatting","__typename":"Game"},"id":"1701662946","lengthSeconds":8494,"owner":{"displayName":"MaximeBiaggi","id":"119657765","login":"maximebiaggi","profileImageURL":"https:\/\/static-cdn.jtvnw.net\/jtv_user_pictures\/994ba4ea-98ba-4446-a923-164e575ff498-profile_image-50x50.png","primaryColorHex":"0013A3","__typename":"User"},"previewThumbnailURL":"https:\/\/static-cdn.jtvnw.net\/cf_vods\/dgeft87wbj63p\/412dade1b7eb0d02fddb_maximebiaggi_46485027756_1673207991\/\/thumb\/thumb0-320x180.jpg","publishedAt":"2023-01-08T19:59:56Z","self":{"isRestricted":false,"viewingHistory":null,"__typename":"VideoSelfEdge"},"title":"BIENVENU DANS LA CHAINE 2.0 NOUVELLE DA","viewCount":86841,"resourceRestriction":null,"contentTags":[{"id":"6f655045-9989-4ef7-8f85-1edcec42d648","isLanguageTag":true,"localizedName":"French","tagName":"auto___lang_fr","__typename":"Tag"}],"__typename":"Video"},"__typename":"VideoEdge"},{"cursor":null,"node":{"animatedPreviewURL":"https:\/\/dgeft87wbj63p.cloudfront.net\/fbfd7e3748cecfce578b_maximebiaggi_46476158636_1673032209\/storyboards\/1699553898-strip-0.jpg","game":{"boxArtURL":"https:\/\/static-cdn.jtvnw.net\/ttv-boxart\/509658-40x56.jpg","id":"509658","displayName":"Just Chatting","name":"Just Chatting","__typename":"Game"},"id":"1699553898","lengthSeconds":11110,"owner":{"displayName":"MaximeBiaggi","id":"119657765","login":"maximebiaggi","profileImageURL":"https:\/\/static-cdn.jtvnw.net\/jtv_user_pictures\/994ba4ea-98ba-4446-a923-164e575ff498-profile_image-50x50.png","primaryColorHex":"0013A3","__typename":"User"},"previewThumbnailURL":"https:\/\/static-cdn.jtvnw.net\/cf_vods\/dgeft87wbj63p\/fbfd7e3748cecfce578b_maximebiaggi_46476158636_1673032209\/\/thumb\/thumb0-320x180.jpg","publishedAt":"2023-01-06T19:10:14Z","self":{"isRestricted":false,"viewingHistory":null,"__typename":"VideoSelfEdge"},"title":"Aventure Minecraft HARDCORE sauf que je suis dans un bloc de 16x16 qui grandit chaque nuit + chat GPT","viewCount":72858,"resourceRestriction":null,"contentTags":[{"id":"6f655045-9989-4ef7-8f85-1edcec42d648","isLanguageTag":true,"localizedName":"French","tagName":"auto___lang_fr","__typename":"Tag"}],"__typename":"Video"},"__typename":"VideoEdge"},{"cursor":null,"node":{"animatedPreviewURL":"https:\/\/dgeft87wbj63p.cloudfront.net\/75b1e65617ec2fad4a92_maximebiaggi_46468254108_1672854260\/storyboards\/1697542301-strip-0.jpg","game":{"boxArtURL":"https:\/\/static-cdn.jtvnw.net\/ttv-boxart\/509658-40x56.jpg","id":"509658","displayName":"Just Chatting","name":"Just Chatting","__typename":"Game"},"id":"1697542301","lengthSeconds":7298,"owner":{"displayName":"MaximeBiaggi","id":"119657765","login":"maximebiaggi","profileImageURL":"https:\/\/static-cdn.jtvnw.net\/jtv_user_pictures\/994ba4ea-98ba-4446-a923-164e575ff498-profile_image-50x50.png","primaryColorHex":"0013A3","__typename":"User"},"previewThumbnailURL":"https:\/\/static-cdn.jtvnw.net\/cf_vods\/dgeft87wbj63p\/75b1e65617ec2fad4a92_maximebiaggi_46468254108_1672854260\/\/thumb\/thumb0-320x180.jpg","publishedAt":"2023-01-04T17:44:24Z","self":{"isRestricted":false,"viewingHistory":null,"__typename":"VideoSelfEdge"},"title":"C'est la rentr\u00e9e !! !youtube","viewCount":54017,"resourceRestriction":null,"contentTags":[],"__typename":"Video"},"__typename":"VideoEdge"},{"cursor":null,"node":{"animatedPreviewURL":"https:\/\/dgeft87wbj63p.cloudfront.net\/c098bc0b4e6d3c7d0ae8_maximebiaggi_46422170156_1671565814\/storyboards\/1684366132-strip-0.jpg","game":{"boxArtURL":"https:\/\/static-cdn.jtvnw.net\/ttv-boxart\/509658-40x56.jpg","id":"509658","displayName":"Just Chatting","name":"Just Chatting","__typename":"Game"},"id":"1684366132","lengthSeconds":5080,"owner":{"displayName":"MaximeBiaggi","id":"119657765","login":"maximebiaggi","profileImageURL":"https:\/\/static-cdn.jtvnw.net\/jtv_user_pictures\/994ba4ea-98ba-4446-a923-164e575ff498-profile_image-50x50.png","primaryColorHex":"0013A3","__typename":"User"},"previewThumbnailURL":"https:\/\/static-cdn.jtvnw.net\/cf_vods\/dgeft87wbj63p\/c098bc0b4e6d3c7d0ae8_maximebiaggi_46422170156_1671565814\/\/thumb\/thumb0-320x180.jpg","publishedAt":"2022-12-20T19:50:19Z","self":{"isRestricted":false,"viewingHistory":null,"__typename":"VideoSelfEdge"},"title":"Repas de No\u00ebl avec les copains en direct des Champs-Elys\u00e9e ! Plein de cadeaux \u00e0 gagner, dress code CHIC et CHOC !puma !hasbro","viewCount":140381,"resourceRestriction":null,"contentTags":[{"id":"6f655045-9989-4ef7-8f85-1edcec42d648","isLanguageTag":true,"localizedName":"French","tagName":"auto___lang_fr","__typename":"Tag"}],"__typename":"Video"},"__typename":"VideoEdge"},{"cursor":null,"node":{"animatedPreviewURL":"https:\/\/dgeft87wbj63p.cloudfront.net\/52fc39e89bdc5b7dca85_maximebiaggi_46422145788_1671565540\/storyboards\/1684362593-strip-0.jpg","game":{"boxArtURL":"https:\/\/static-cdn.jtvnw.net\/ttv-boxart\/509658-40x56.jpg","id":"509658","displayName":"Just Chatting","name":"Just Chatting","__typename":"Game"},"id":"1684362593","lengthSeconds":190,"owner":{"displayName":"MaximeBiaggi","id":"119657765","login":"maximebiaggi","profileImageURL":"https:\/\/static-cdn.jtvnw.net\/jtv_user_pictures\/994ba4ea-98ba-4446-a923-164e575ff498-profile_image-50x50.png","primaryColorHex":"0013A3","__typename":"User"},"previewThumbnailURL":"https:\/\/static-cdn.jtvnw.net\/cf_vods\/dgeft87wbj63p\/52fc39e89bdc5b7dca85_maximebiaggi_46422145788_1671565540\/\/thumb\/thumb0-320x180.jpg","publishedAt":"2022-12-20T19:45:45Z","self":{"isRestricted":false,"viewingHistory":null,"__typename":"VideoSelfEdge"},"title":"Repas de No\u00ebl avec les copains en direct des Champs-Elys\u00e9e ! Plein de cadeaux \u00e0 gagner, dress code CHIC et CHOC !puma !hasbro","viewCount":46965,"resourceRestriction":null,"contentTags":[{"id":"6f655045-9989-4ef7-8f85-1edcec42d648","isLanguageTag":true,"localizedName":"French","tagName":"auto___lang_fr","__typename":"Tag"}],"__typename":"Video"},"__typename":"VideoEdge"},{"cursor":null,"node":{"animatedPreviewURL":"https:\/\/dgeft87wbj63p.cloudfront.net\/9b007ce9f860bf9fae30_maximebiaggi_46421799372_1671562203\/storyboards\/1684315091-strip-0.jpg","game":{"boxArtURL":"https:\/\/static-cdn.jtvnw.net\/ttv-boxart\/509658-40x56.jpg","id":"509658","displayName":"Just Chatting","name":"Just Chatting","__typename":"Game"},"id":"1684315091","lengthSeconds":3322,"owner":{"displayName":"MaximeBiaggi","id":"119657765","login":"maximebiaggi","profileImageURL":"https:\/\/static-cdn.jtvnw.net\/jtv_user_pictures\/994ba4ea-98ba-4446-a923-164e575ff498-profile_image-50x50.png","primaryColorHex":"0013A3","__typename":"User"},"previewThumbnailURL":"https:\/\/static-cdn.jtvnw.net\/cf_vods\/dgeft87wbj63p\/9b007ce9f860bf9fae30_maximebiaggi_46421799372_1671562203\/\/thumb\/thumb0-320x180.jpg","publishedAt":"2022-12-20T18:50:07Z","self":{"isRestricted":false,"viewingHistory":null,"__typename":"VideoSelfEdge"},"title":"Repas de No\u00ebl avec les copains en direct des Champs-Elys\u00e9e ! Plein de cadeaux \u00e0 gagner, dress code CHIC et CHOC !puma !hasbro","viewCount":91020,"resourceRestriction":null,"contentTags":[],"__typename":"Video"},"__typename":"VideoEdge"},{"cursor":null,"node":{"animatedPreviewURL":"https:\/\/dgeft87wbj63p.cloudfront.net\/069b303bf4d77fff68ec_maximebiaggi_46405702508_1671123579\/storyboards\/1679796933-strip-0.jpg","game":{"boxArtURL":"https:\/\/static-cdn.jtvnw.net\/ttv-boxart\/509658-40x56.jpg","id":"509658","displayName":"Just Chatting","name":"Just Chatting","__typename":"Game"},"id":"1679796933","lengthSeconds":8456,"owner":{"displayName":"MaximeBiaggi","id":"119657765","login":"maximebiaggi","profileImageURL":"https:\/\/static-cdn.jtvnw.net\/jtv_user_pictures\/994ba4ea-98ba-4446-a923-164e575ff498-profile_image-50x50.png","primaryColorHex":"0013A3","__typename":"User"},"previewThumbnailURL":"https:\/\/static-cdn.jtvnw.net\/cf_vods\/dgeft87wbj63p\/069b303bf4d77fff68ec_maximebiaggi_46405702508_1671123579\/\/thumb\/thumb0-320x180.jpg","publishedAt":"2022-12-15T16:59:44Z","self":{"isRestricted":false,"viewingHistory":null,"__typename":"VideoSelfEdge"},"title":"BLABAL PUIS ON JOUE A THE WITCHER 3 (JE DECOUVRE LE JEU) #GeForceNOW #RTXOn #ad","viewCount":33038,"resourceRestriction":null,"contentTags":[],"__typename":"Video"},"__typename":"VideoEdge"},{"cursor":null,"node":{"animatedPreviewURL":"https:\/\/dgeft87wbj63p.cloudfront.net\/2c259dc85a0c6ee8d2f9_maximebiaggi_46395176700_1670776640\/storyboards\/1676363612-strip-0.jpg","game":{"boxArtURL":"https:\/\/static-cdn.jtvnw.net\/ttv-boxart\/27471_IGDB-40x56.jpg","id":"27471","displayName":"Minecraft","name":"Minecraft","__typename":"Game"},"id":"1676363612","lengthSeconds":21474,"owner":{"displayName":"MaximeBiaggi","id":"119657765","login":"maximebiaggi","profileImageURL":"https:\/\/static-cdn.jtvnw.net\/jtv_user_pictures\/994ba4ea-98ba-4446-a923-164e575ff498-profile_image-50x50.png","primaryColorHex":"0013A3","__typename":"User"},"previewThumbnailURL":"https:\/\/static-cdn.jtvnw.net\/cf_vods\/dgeft87wbj63p\/2c259dc85a0c6ee8d2f9_maximebiaggi_46395176700_1670776640\/\/thumb\/thumb0-320x180.jpg","publishedAt":"2022-12-11T16:37:25Z","self":{"isRestricted":false,"viewingHistory":null,"__typename":"VideoSelfEdge"},"title":"ON SENTRAINE AVEC THEOUS CE SOIR TOURNOI A 1 MILLION DEURO CHEZ INOXTAG","viewCount":121565,"resourceRestriction":null,"contentTags":[],"__typename":"Video"},"__typename":"VideoEdge"},{"cursor":null,"node":{"animatedPreviewURL":"https:\/\/dgeft87wbj63p.cloudfront.net\/a708e5533f0f6360afba_maximebiaggi_46380911932_1670426216\/storyboards\/1672729839-strip-0.jpg","game":{"boxArtURL":"https:\/\/static-cdn.jtvnw.net\/ttv-boxart\/509658-40x56.jpg","id":"509658","displayName":"Just Chatting","name":"Just Chatting","__typename":"Game"},"id":"1672729839","lengthSeconds":8616,"owner":{"displayName":"MaximeBiaggi","id":"119657765","login":"maximebiaggi","profileImageURL":"https:\/\/static-cdn.jtvnw.net\/jtv_user_pictures\/994ba4ea-98ba-4446-a923-164e575ff498-profile_image-50x50.png","primaryColorHex":"0013A3","__typename":"User"},"previewThumbnailURL":"https:\/\/static-cdn.jtvnw.net\/cf_vods\/dgeft87wbj63p\/a708e5533f0f6360afba_maximebiaggi_46380911932_1670426216\/\/thumb\/thumb0-320x180.jpg","publishedAt":"2022-12-07T15:17:01Z","self":{"isRestricted":false,"viewingHistory":null,"__typename":"VideoSelfEdge"},"title":"PRELIVE DISCUSSION + entrainement pour le masterkill","viewCount":45872,"resourceRestriction":null,"contentTags":[{"id":"6f655045-9989-4ef7-8f85-1edcec42d648","isLanguageTag":true,"localizedName":"French","tagName":"auto___lang_fr","__typename":"Tag"}],"__typename":"Video"},"__typename":"VideoEdge"},{"cursor":null,"node":{"animatedPreviewURL":"https:\/\/dgeft87wbj63p.cloudfront.net\/68b7dc54827abf3ce5b2_maximebiaggi_46375169724_1670266207\/storyboards\/1671164713-strip-0.jpg","game":{"boxArtURL":"https:\/\/static-cdn.jtvnw.net\/ttv-boxart\/509658-40x56.jpg","id":"509658","displayName":"Just Chatting","name":"Just Chatting","__typename":"Game"},"id":"1671164713","lengthSeconds":8671,"owner":{"displayName":"MaximeBiaggi","id":"119657765","login":"maximebiaggi","profileImageURL":"https:\/\/static-cdn.jtvnw.net\/jtv_user_pictures\/994ba4ea-98ba-4446-a923-164e575ff498-profile_image-50x50.png","primaryColorHex":"0013A3","__typename":"User"},"previewThumbnailURL":"https:\/\/static-cdn.jtvnw.net\/cf_vods\/dgeft87wbj63p\/68b7dc54827abf3ce5b2_maximebiaggi_46375169724_1670266207\/\/thumb\/thumb0-320x180.jpg","publishedAt":"2022-12-05T18:50:12Z","self":{"isRestricted":false,"viewingHistory":null,"__typename":"VideoSelfEdge"},"title":"ZEN !!! ON EST AVEC INOXTAG (et tout l\u2019equipage\u2026.. \ud83d\ude0e\ud83d\ude0e\ud83d\ude0e) bcp de surprises \ud83e\udef5\ud83c\udffb","viewCount":282944,"resourceRestriction":null,"contentTags":[],"__typename":"Video"},"__typename":"VideoEdge"},{"cursor":null,"node":{"animatedPreviewURL":"https:\/\/dgeft87wbj63p.cloudfront.net\/f2292abb70c8d259d8ae_maximebiaggi_46347076828_1669557997\/storyboards\/1664096264-strip-0.jpg","game":{"boxArtURL":"https:\/\/static-cdn.jtvnw.net\/ttv-boxart\/509658-40x56.jpg","id":"509658","displayName":"Just Chatting","name":"Just Chatting","__typename":"Game"},"id":"1664096264","lengthSeconds":11970,"owner":{"displayName":"MaximeBiaggi","id":"119657765","login":"maximebiaggi","profileImageURL":"https:\/\/static-cdn.jtvnw.net\/jtv_user_pictures\/994ba4ea-98ba-4446-a923-164e575ff498-profile_image-50x50.png","primaryColorHex":"0013A3","__typename":"User"},"previewThumbnailURL":"https:\/\/static-cdn.jtvnw.net\/cf_vods\/dgeft87wbj63p\/f2292abb70c8d259d8ae_maximebiaggi_46347076828_1669557997\/\/thumb\/thumb0-320x180.jpg","publishedAt":"2022-11-27T14:06:45Z","self":{"isRestricted":false,"viewingHistory":null,"__typename":"VideoSelfEdge"},"title":"abonnez vous sur instagram svp","viewCount":54212,"resourceRestriction":null,"contentTags":[],"__typename":"Video"},"__typename":"VideoEdge"},{"cursor":null,"node":{"animatedPreviewURL":"https:\/\/dgeft87wbj63p.cloudfront.net\/5efa0b62e6772082b5ee_maximebiaggi_46330152508_1669126765\/storyboards\/1659833791-strip-0.jpg","game":{"boxArtURL":"https:\/\/static-cdn.jtvnw.net\/ttv-boxart\/509658-40x56.jpg","id":"509658","displayName":"Just Chatting","name":"Just Chatting","__typename":"Game"},"id":"1659833791","lengthSeconds":12259,"owner":{"displayName":"MaximeBiaggi","id":"119657765","login":"maximebiaggi","profileImageURL":"https:\/\/static-cdn.jtvnw.net\/jtv_user_pictures\/994ba4ea-98ba-4446-a923-164e575ff498-profile_image-50x50.png","primaryColorHex":"0013A3","__typename":"User"},"previewThumbnailURL":"https:\/\/static-cdn.jtvnw.net\/cf_vods\/dgeft87wbj63p\/5efa0b62e6772082b5ee_maximebiaggi_46330152508_1669126765\/\/thumb\/thumb0-320x180.jpg","publishedAt":"2022-11-22T14:19:30Z","self":{"isRestricted":false,"viewingHistory":null,"__typename":"VideoSelfEdge"},"title":"La maladie m'a vaincu. Petit debrief de zen et ptites games sur LoL","viewCount":42315,"resourceRestriction":null,"contentTags":[{"id":"6f655045-9989-4ef7-8f85-1edcec42d648","isLanguageTag":true,"localizedName":"French","tagName":"auto___lang_fr","__typename":"Tag"}],"__typename":"Video"},"__typename":"VideoEdge"},{"cursor":null,"node":{"animatedPreviewURL":"https:\/\/dgeft87wbj63p.cloudfront.net\/d582f7169fa952fe5257_maximebiaggi_46327881660_1669056641\/storyboards\/1659154282-strip-0.jpg","game":{"boxArtURL":"https:\/\/static-cdn.jtvnw.net\/ttv-boxart\/509658-40x56.jpg","id":"509658","displayName":"Just Chatting","name":"Just Chatting","__typename":"Game"},"id":"1659154282","lengthSeconds":8690,"owner":{"displayName":"MaximeBiaggi","id":"119657765","login":"maximebiaggi","profileImageURL":"https:\/\/static-cdn.jtvnw.net\/jtv_user_pictures\/994ba4ea-98ba-4446-a923-164e575ff498-profile_image-50x50.png","primaryColorHex":"0013A3","__typename":"User"},"previewThumbnailURL":"https:\/\/static-cdn.jtvnw.net\/cf_vods\/dgeft87wbj63p\/d582f7169fa952fe5257_maximebiaggi_46327881660_1669056641\/\/thumb\/thumb0-320x180.jpg","publishedAt":"2022-11-21T18:50:45Z","self":{"isRestricted":false,"viewingHistory":null,"__typename":"VideoSelfEdge"},"title":"ZEN !! Le late show chicos avec TERRACID SIUUU. Bcp de choses pr\u00e9vues comme d'hab !! \ud83d\ude0e","viewCount":221688,"resourceRestriction":null,"contentTags":[{"id":"6f655045-9989-4ef7-8f85-1edcec42d648","isLanguageTag":true,"localizedName":"French","tagName":"auto___lang_fr","__typename":"Tag"}],"__typename":"Video"},"__typename":"VideoEdge"},{"cursor":null,"node":{"animatedPreviewURL":"https:\/\/dgeft87wbj63p.cloudfront.net\/9a88d66ed056409477c6_maximebiaggi_46318485628_1668848808\/storyboards\/1656984897-strip-0.jpg","game":{"boxArtURL":"https:\/\/static-cdn.jtvnw.net\/ttv-boxart\/509658-40x56.jpg","id":"509658","displayName":"Just Chatting","name":"Just Chatting","__typename":"Game"},"id":"1656984897","lengthSeconds":11326,"owner":{"displayName":"MaximeBiaggi","id":"119657765","login":"maximebiaggi","profileImageURL":"https:\/\/static-cdn.jtvnw.net\/jtv_user_pictures\/994ba4ea-98ba-4446-a923-164e575ff498-profile_image-50x50.png","primaryColorHex":"0013A3","__typename":"User"},"previewThumbnailURL":"https:\/\/static-cdn.jtvnw.net\/cf_vods\/dgeft87wbj63p\/9a88d66ed056409477c6_maximebiaggi_46318485628_1668848808\/\/thumb\/thumb0-320x180.jpg","publishedAt":"2022-11-19T09:06:53Z","self":{"isRestricted":false,"viewingHistory":null,"__typename":"VideoSelfEdge"},"title":"MAXITINAL ON SENTRAINE SUR CAMILLE POUR LA NOUVELLE SAISON","viewCount":32068,"resourceRestriction":null,"contentTags":[{"id":"6f655045-9989-4ef7-8f85-1edcec42d648","isLanguageTag":true,"localizedName":"French","tagName":"auto___lang_fr","__typename":"Tag"}],"__typename":"Video"},"__typename":"VideoEdge"},{"cursor":null,"node":{"animatedPreviewURL":"https:\/\/dgeft87wbj63p.cloudfront.net\/59dbc98fe4643774eeaf_maximebiaggi_46315580476_1668791420\/storyboards\/1656267207-strip-0.jpg","game":{"boxArtURL":"https:\/\/static-cdn.jtvnw.net\/ttv-boxart\/509658-40x56.jpg","id":"509658","displayName":"Just Chatting","name":"Just Chatting","__typename":"Game"},"id":"1656267207","lengthSeconds":8540,"owner":{"displayName":"MaximeBiaggi","id":"119657765","login":"maximebiaggi","profileImageURL":"https:\/\/static-cdn.jtvnw.net\/jtv_user_pictures\/994ba4ea-98ba-4446-a923-164e575ff498-profile_image-50x50.png","primaryColorHex":"0013A3","__typename":"User"},"previewThumbnailURL":"https:\/\/static-cdn.jtvnw.net\/cf_vods\/dgeft87wbj63p\/59dbc98fe4643774eeaf_maximebiaggi_46315580476_1668791420\/\/thumb\/thumb0-320x180.jpg","publishedAt":"2022-11-18T17:10:25Z","self":{"isRestricted":false,"viewingHistory":null,"__typename":"VideoSelfEdge"},"title":"On retente le d\u00e9fi 100 jours sur minecraft hardcore coolos non venez sur insta aussi","viewCount":30391,"resourceRestriction":null,"contentTags":[],"__typename":"Video"},"__typename":"VideoEdge"},{"cursor":null,"node":{"animatedPreviewURL":"https:\/\/dgeft87wbj63p.cloudfront.net\/5db343bc545daaf1127e_maximebiaggi_46300037484_1668443728\/storyboards\/1652603519-strip-0.jpg","game":{"boxArtURL":"https:\/\/static-cdn.jtvnw.net\/ttv-boxart\/21779-40x56.jpg","id":"21779","displayName":"League of Legends","name":"League of Legends","__typename":"Game"},"id":"1652603519","lengthSeconds":26277,"owner":{"displayName":"MaximeBiaggi","id":"119657765","login":"maximebiaggi","profileImageURL":"https:\/\/static-cdn.jtvnw.net\/jtv_user_pictures\/994ba4ea-98ba-4446-a923-164e575ff498-profile_image-50x50.png","primaryColorHex":"0013A3","__typename":"User"},"previewThumbnailURL":"https:\/\/static-cdn.jtvnw.net\/cf_vods\/dgeft87wbj63p\/5db343bc545daaf1127e_maximebiaggi_46300037484_1668443728\/\/thumb\/thumb0-320x180.jpg","publishedAt":"2022-11-14T16:35:33Z","self":{"isRestricted":false,"viewingHistory":null,"__typename":"VideoSelfEdge"},"title":"c'est le dernier jour : tryhard. pas de blagues. rien.","viewCount":95634,"resourceRestriction":null,"contentTags":[{"id":"6f655045-9989-4ef7-8f85-1edcec42d648","isLanguageTag":true,"localizedName":"French","tagName":"auto___lang_fr","__typename":"Tag"}],"__typename":"Video"},"__typename":"VideoEdge"},{"cursor":null,"node":{"animatedPreviewURL":"https:\/\/dgeft87wbj63p.cloudfront.net\/98a15f1560c7a40e83d4_maximebiaggi_46253813292_1667407582\/storyboards\/1641490398-strip-0.jpg","game":{"boxArtURL":"https:\/\/static-cdn.jtvnw.net\/ttv-boxart\/509658-40x56.jpg","id":"509658","displayName":"Just Chatting","name":"Just Chatting","__typename":"Game"},"id":"1641490398","lengthSeconds":19382,"owner":{"displayName":"MaximeBiaggi","id":"119657765","login":"maximebiaggi","profileImageURL":"https:\/\/static-cdn.jtvnw.net\/jtv_user_pictures\/994ba4ea-98ba-4446-a923-164e575ff498-profile_image-50x50.png","primaryColorHex":"0013A3","__typename":"User"},"previewThumbnailURL":"https:\/\/static-cdn.jtvnw.net\/cf_vods\/dgeft87wbj63p\/98a15f1560c7a40e83d4_maximebiaggi_46253813292_1667407582\/\/thumb\/thumb0-320x180.jpg","publishedAt":"2022-11-02T16:46:27Z","self":{"isRestricted":false,"viewingHistory":null,"__typename":"VideoSelfEdge"},"title":"Vous voulez de l'horreur ? Vous allez en avoir. Or 1 start platine bientot.","viewCount":46528,"resourceRestriction":null,"contentTags":[{"id":"6f655045-9989-4ef7-8f85-1edcec42d648","isLanguageTag":true,"localizedName":"French","tagName":"auto___lang_fr","__typename":"Tag"}],"__typename":"Video"},"__typename":"VideoEdge"}],"pageInfo":{"hasNextPage":false,"__typename":"PageInfo"},"__typename":"VideoConnection"},"__typename":"User"}},"extensions":{"durationMilliseconds":100,"operationName":"FilterableVideoTower_Videos","requestID":"01GPNWWRB9F7Z7K2CXFY4JDD8Q"}}],"timestamp":1673624707}